README.md
setup.py
qualified_name_extractor/__init__.py
qualified_name_extractor.egg-info/PKG-INFO
qualified_name_extractor.egg-info/SOURCES.txt
qualified_name_extractor.egg-info/dependency_links.txt
qualified_name_extractor.egg-info/requires.txt
qualified_name_extractor.egg-info/top_level.txt
qualified_name_extractor/code_based/ASTParseBasedWithGraphBaker.py
qualified_name_extractor/code_based/ASTParseCodeBasedWithGraphBaker.py
qualified_name_extractor/code_based/BakerGraphAccessor.py
qualified_name_extractor/code_based/CodeBasedWithGraphBaker.py
qualified_name_extractor/code_based/__init__.py
qualified_name_extractor/code_based/base.py