Metadata-Version: 1.0
Name: qualified-name-extractor
Version: 0.1.3.3
Summary: extract qualified name
Home-page: https://github.com/FudanSELab/ExtractQualifiedName
Author: lvxiaoxiang
Author-email: 1547554745@qq.com
License: Apache License, Version 2.0
Keywords: extract,qualified name,extractor
Platform: any
